[{"id":1,"scoutname":"zachary","scoutteam":5895,"team":69,"match":12,"matchtype":2,"breakdown":false,"noshow":false,"leave":true,"autol1success":3,"autol1fail":1,"autol2success":2,"autol2fail":0,"autol3success":1,"autol3fail":2,"autol4success":3,"autol4fail":0,"autoalgaeremoved":1,"autoprocessorsuccess":2,"autoprocessorfail":1,"autonetsuccess":3,"autonetfail":0,"telel1success":4,"telel1fail":2,"telel2success":3,"telel2fail":1,"telel3success":2,"telel3fail":3,"telel4success":3,"telel4fail":0,"telealgaeremoved":2,"teleprocessorsuccess":1,"teleprocessorfail":1,"telenetsuccess":2,"telenetfail":0,"hpsuccess":5,"hpfail":0,"endlocation":2,"coralspeed":4,"processorspeed":3,"netspeed":5,"algaeremovalspeed":2,"climbspeed":3,"maneuverability":4,"defenseplayed":2,"defenseevasion":3,"aggression":1,"cagehazard":2,"coralgrndintake":true,"coralstationintake":false,"lollipop":true,"algaegrndintake":true,"algaehighreefintake":false,"algaelowreefintake":false,"generalcomments":"Performed well in auto but struggled with teleop.","breakdowncomments":null,"defensecomments":"Played strong defense."},{"id":16,"scoutname":"zachary","scoutteam":5895,"team":1111,"match":1,"matchtype":2,"breakdown":null,"noshow":true,"leave":null,"autol1success":null,"autol1fail":null,"autol2success":null,"autol2fail":null,"autol3success":null,"autol3fail":null,"autol4success":null,"autol4fail":null,"autoalgaeremoved":null,"autoprocessorsuccess":null,"autoprocessorfail":null,"autonetsuccess":null,"autonetfail":null,"telel1success":null,"telel1fail":null,"telel2success":null,"telel2fail":null,"telel3success":null,"telel3fail":null,"telel4success":null,"telel4fail":null,"telealgaeremoved":null,"teleprocessorsuccess":null,"teleprocessorfail":null,"telenetsuccess":null,"telenetfail":null,"hpsuccess":null,"hpfail":null,"endlocation":null,"coralspeed":null,"processorspeed":null,"netspeed":null,"algaeremovalspeed":null,"climbspeed":null,"maneuverability":null,"defenseplayed":3,"defenseevasion":null,"aggression":null,"cagehazard":null,"coralgrndintake":null,"coralstationintake":null,"lollipop":null,"algaegrndintake":null,"algaehighreefintake":null,"algaelowreefintake":null,"generalcomments":null,"breakdowncomments":null,"defensecomments":null},{"id":17,"scoutname":"zachary","scoutteam":5895,"team":69,"match":2,"matchtype":2,"breakdown":null,"noshow":true,"leave":null,"autol1success":null,"autol1fail":null,"autol2success":null,"autol2fail":null,"autol3success":null,"autol3fail":null,"autol4success":null,"autol4fail":null,"autoalgaeremoved":null,"autoprocessorsuccess":null,"autoprocessorfail":null,"autonetsuccess":null,"autonetfail":null,"telel1success":null,"telel1fail":null,"telel2success":null,"telel2fail":null,"telel3success":null,"telel3fail":null,"telel4success":null,"telel4fail":null,"telealgaeremoved":null,"teleprocessorsuccess":null,"teleprocessorfail":null,"telenetsuccess":null,"telenetfail":null,"hpsuccess":null,"hpfail":null,"endlocation":null,"coralspeed":null,"processorspeed":null,"netspeed":null,"algaeremovalspeed":null,"climbspeed":null,"maneuverability":null,"defenseplayed":5,"defenseevasion":null,"aggression":null,"cagehazard":null,"coralgrndintake":null,"coralstationintake":null,"lollipop":null,"algaegrndintake":null,"algaehighreefintake":null,"algaelowreefintake":null,"generalcomments":null,"breakdowncomments":null,"defensecomments":null},{"id":18,"scoutname":"zachary","scoutteam":5895,"team":69,"match":2,"matchtype":2,"breakdown":null,"noshow":false,"leave":false,"autol1success":0,"autol1fail":0,"autol2success":0,"autol2fail":0,"autol3success":0,"autol3fail":0,"autol4success":0,"autol4fail":0,"autoalgaeremoved":0,"autoprocessorsuccess":0,"autoprocessorfail":0,"autonetsuccess":0,"autonetfail":0,"telel1success":0,"telel1fail":0,"telel2success":0,"telel2fail":0,"telel3success":0,"telel3fail":0,"telel4success":0,"telel4fail":0,"telealgaeremoved":0,"teleprocessorsuccess":0,"teleprocessorfail":0,"telenetsuccess":0,"telenetfail":0,"hpsuccess":null,"hpfail":null,"endlocation":null,"coralspeed":null,"processorspeed":null,"netspeed":null,"algaeremovalspeed":null,"climbspeed":null,"maneuverability":null,"defenseplayed":4,"defenseevasion":null,"aggression":null,"cagehazard":null,"coralgrndintake":false,"coralstationintake":false,"lollipop":false,"algaegrndintake":false,"algaehighreefintake":false,"algaelowreefintake":false,"generalcomments":null,"breakdowncomments":null,"defensecomments":"das"},{"id":21,"scoutname":"zachary","scoutteam":5895,"team":69,"match":69,"matchtype":2,"breakdown":null,"noshow":false,"leave":true,"autol1success":1,"autol1fail":1,"autol2success":1,"autol2fail":1,"autol3success":1,"autol3fail":1,"autol4success":1,"autol4fail":1,"autoalgaeremoved":1,"autoprocessorsuccess":1,"autoprocessorfail":1,"autonetsuccess":1,"autonetfail":1,"telel1success":1,"telel1fail":1,"telel2success":1,"telel2fail":1,"telel3success":1,"telel3fail":1,"telel4success":1,"telel4fail":1,"telealgaeremoved":1,"teleprocessorsuccess":1,"teleprocessorfail":1,"telenetsuccess":1,"telenetfail":1,"hpsuccess":null,"hpfail":null,"endlocation":null,"coralspeed":null,"processorspeed":null,"netspeed":null,"algaeremovalspeed":null,"climbspeed":null,"maneuverability":null,"defenseplayed":null,"defenseevasion":null,"aggression":null,"cagehazard":null,"coralgrndintake":true,"coralstationintake":true,"lollipop":false,"algaegrndintake":true,"algaehighreefintake":true,"algaelowreefintake":true,"generalcomments":null,"breakdowncomments":null,"defensecomments":null},{"id":22,"scoutname":"poop","scoutteam":5895,"team":166464,"match":323565,"matchtype":2,"breakdown":null,"noshow":true,"leave":null,"autol1success":null,"autol1fail":null,"autol2success":null,"autol2fail":null,"autol3success":null,"autol3fail":null,"autol4success":null,"autol4fail":null,"autoalgaeremoved":null,"autoprocessorsuccess":null,"autoprocessorfail":null,"autonetsuccess":null,"autonetfail":null,"telel1success":null,"telel1fail":null,"telel2success":null,"telel2fail":null,"telel3success":null,"telel3fail":null,"telel4success":null,"telel4fail":null,"telealgaeremoved":null,"teleprocessorsuccess":null,"teleprocessorfail":null,"telenetsuccess":null,"telenetfail":null,"hpsuccess":null,"hpfail":null,"endlocation":null,"coralspeed":null,"processorspeed":null,"netspeed":null,"algaeremovalspeed":null,"climbspeed":null,"maneuverability":null,"defenseplayed":null,"defenseevasion":null,"aggression":null,"cagehazard":null,"coralgrndintake":null,"coralstationintake":null,"lollipop":null,"algaegrndintake":null,"algaehighreefintake":null,"algaelowreefintake":null,"generalcomments":null,"breakdowncomments":null,"defensecomments":null}]